utls/__init__.py
utls/click_n_crop.py
utls/open_n_load_mag_qsm_2files.py
utls/show_mri_3d.py
crop_nifti_by_mouse_click-0.0.3.dist-info/METADATA
crop_nifti_by_mouse_click-0.0.3.dist-info/WHEEL
crop_nifti_by_mouse_click-0.0.3.dist-info/top_level.txt
crop_nifti_by_mouse_click-0.0.3.dist-info/RECORD
